Workbook

Sheet BRANCH PROFILE FULL FORMAT
B2: बैंक ऑफ इंडिया / BANK OF INDIA
B3: आयोजना विभाग, तेलंगाना अंचल / PLANNING DEPARTMENT, TELANGANA ZONE
B5: PAGE-1
B7: BRANCH PROFILE AS ON | F7: 16-Jan-2026 | I7: (Amount Rs. in Lakhs)
B8: Remark's: HR Data is as on 15.09.2025
B10: शाखा विवरण / BRANCH DETAILS
B11: शाखा का नाम / Branch Name | E11: Select Branch | I11: BR. CODE | J11: =INDEX(DATA!A:A,MATCH($E$11,DATA!B:B,0)) | L11: ←ENTER BRANCH CODE HERE
B13: जमा / DEPOSITS
C14: Mar-23 Actual | D14: Mar-24 Actual | E14: Mar-25 Actual | F14: 24-Nov-25 Budget | G14: 24-Nov-25 Actual | H14: GAP | I14: VAR Over Mar-25 | J14: Budget Mar-26
B15: जमा पूंजी / SAVINGS | C15: 0 | D15: 0 | E15: 0 | F15: 0 | G15: 0 | H15: =F15-E15 | I15: =F15-D15 | J15: 0
B16: चालू / CURRENT | C16: 0 | D16: 0 | E16: 0 | F16: 0 | G16: 0 | H16: =F16-E16 | I16: =F16-D16 | J16: 0
B17: चलती / CASA | C17: 0 | D17: 0 | E17: 0 | F17: 0 | G17: 0 | H17: =F17-E17 | I17: =F17-D17 | J17: 0
B18: खुदरा सावधि जमा / RETAIL TD | C18: 0 | D18: 0 | E18: 0 | F18: 0 | G18: 0 | H18: =F18-E18 | I18: =F18-D18 | J18: 0
B19: सावधि जमा / TERM DEPOSITS | C19: 0 | D19: 0 | E19: 0 | F19: 0 | G19: 0 | H19: =F19-E19 | I19: =F19-D19 | J19: 0
B20: कुल जमाराशि / TOTAL DEPOSITS | C20: 0 | D20: 0 | E20: 0 | F20: 0 | G20: 0 | H20: =F20-E20 | I20: =F20-D20 | J20: 0
B22: अग्रिम / ADVANCES
C23: Mar-23 Actual | D23: Mar-24 Actual | E23: Mar-25 Actual | F23: 24-Nov-25 Budget | G23: 24-Nov-25 Actual | H23: GAP | I23: VAR Over Mar-25 | J23: Budget Mar-26
B24: कुल अग्रिम / TOTAL ADVANCES | C24: 0 | D24: 0 | E24: 0 | F24: 0 | G24: 0 | H24: =F24-E24 | I24: =F24-D24 | J24: 0
B25: सुवर्ण ऋण / GOLD LOAN | C25: 0 | D25: 0 | E25: 0 | F25: 0 | G25: 0 | H25: =F25-E25 | I25: =F25-D25 | J25: 0
B26: कृषि / AGRICULTURE | C26: 0 | D26: 0 | E26: 0 | F26: 0 | G26: 0 | H26: =F26-E26 | I26: =F26-D26 | J26: 0
B27: एमएसएमई / MSME | C27: 0 | D27: 0 | E27: 0 | F27: 0 | G27: 0 | H27: =F27-E27 | I27: =F27-D27 | J27: 0
B28: कुल खुदरा / TOTAL RETAIL | C28: 0 | D28: 0 | E28: 0 | F28: 0 | G28: 0 | H28: =F28-E28 | I28: =F28-D28 | J28: 0
B29: कॉर्पोरेट एवं अन्य /C & IC OTHERS | C29: 0 | D29: 0 | E29: 0 | F29: 0 | G29: 0 | H29: =F29-E29 | I29: =F29-D29 | J29: 0

Sheet DATA
A1: Branch_ID | B1: Branch_Name | C1: Zone | D1: Grade | E1: Score | F1: Total_Deposits | G1: Deposit_Target | H1: Advances | I1: Advance_Target | J1: NPA_Percent | K1: Profit_Per_Staff | L1: AI_Insights | M1: AI_Recommendations | N1: Priority_Actions
A2: B1001 | B2: Branch_1 | C2: Central | D2: B | E2: 75 | F2: 1174.35 | G2: 946.05 | H2: 1892.43 | I2: 1522.13 | J2: 5.44 | K2: 0.50742857 | L2: ✅ Deposits at 124.1% - On track | ✅ Advances at 124.3% - Strong performance | 🟡 NPA at 5.44% - High stress zone | M2: Maintain momentum through customer engagement | Aggressive recovery campaigns | Weekly recovery review meetings | CRITICAL: Review cost structure | Staff productivity enhancement needed | N2: 1
A3: B1002 | B3: Branch_2 | C3: Central | D3: A | E3: 100 | F3: 879.69 | G3: 668.71 | H3: 1287.25 | I3: 1197.78 | J3: 1.3 | K3: 7.6117647 | L3: ✅ Deposits at 131.6% - On track | ✅ Advances at 107.5% - Strong performance | ✅ NPA at 1.3% - Excellent asset quality | M3: Maintain momentum through customer engagement | N3: 1
A4: B1003 | B4: Branch_3 | C4: North | D4: A | E4: 93.1 | F4: 2002.69 | G4: 2219.18 | H4: 360.84 | I4: 429.1 | J4: 1.13 | K4: 9.0169767 | L4: 🟡 Deposits at 90.2% - Need push (₹216Cr gap) | 🔴 CRITICAL: Advances at 84.1% (Need ₹68Cr) | ✅ NPA at 1.13% - Excellent asset quality | M4: Intensify retail deposit campaigns | Focus on salary account acquisition | URGENT: Accelerate loan disbursement | Focus on MSME and Agriculture loans | Organize loan camps (2 per month) | N4: 2
A5: B1004 | B5: Branch_4 | C5: South | D5: B | E5: 74.2 | F5: 1431.68 | G5: 1544.04 | H5: 1684.38 | I5: 1971.05 | J5: 8.35 | K5: 5.4928302 | L5: 🟡 Deposits at 92.7% - Need push (₹112Cr gap) | 🟡 Advances at 85.5% - Below target | 🔴 CRITICAL: NPA at 8.35% - Immediate action needed | M5: Intensify retail deposit campaigns | Focus on salary account acquisition | Push quality credit growth | Tap MSME sector opportunities | URGENT: Constitute daily recovery task force | N5: 2
A6: B1005 | B6: Branch_5 | C6: West | D6: C | E6: 62.6 | F6: 563.06 | G6: 674.81 | H6: 1667.36 | I6: 2024.6 | J6: 10.99 | K6: 3.3571875 | L6: 🔴 CRITICAL: Deposits at 83.4% of target (Need ₹112Cr more) | 🔴 CRITICAL: Advances at 82.4% (Need ₹357Cr) | 🔴 CRITICAL: NPA at 10.99% - Immediate action needed | M6: URGENT: Launch deposit mobilization drive within 7 days | Target 5 new CASA accounts daily | Conduct customer meets in catchment area | URGENT: Accelerate loan disbursement | Focus on MSME and Agriculture loans | N6: 3
A7: B1006 | B7: Branch_6 | C7: North | D7: B | E7: 73.7 | F7: 1276.27 | G7: 1115.33 | H7: 667.39 | I7: 890.88 | J7: 7.59 | K7: 6.2707937 | L7: ✅ Deposits at 114.4% - On track | 🔴 CRITICAL: Advances at 74.9% (Need ₹223Cr) | 🔴 CRITICAL: NPA at 7.59% - Immediate action needed | M7: Maintain momentum through customer engagement | URGENT: Accelerate loan disbursement | Focus on MSME and Agriculture loans | Organize loan camps (2 per month) | URGENT: Constitute daily recovery task force | N7: 2
A8: B1007 | B8: Branch_7 | C8: East | D8: B | E8: 70.1 | F8: 1077.43 | G8: 1493.45 | H8: 506.97 | I8: 539.21 | J8: 13.1 | K8: 13.036667 | L8: 🔴 CRITICAL: Deposits at 72.1% of target (Need ₹416Cr more) | 🟡 Advances at 94.0% - Below target | 🔴 CRITICAL: NPA at 13.1% - Immediate action needed | M8: URGENT: Launch deposit mobilization drive within 7 days | Target 5 new CASA accounts daily | Conduct customer meets in catchment area | Push quality credit growth | Tap MSME sector opportunities | N8: 2
A9: B1008 | B9: Branch_8 | C9: East | D9: B | E9: 77.2 | F9: 2364.34 | G9: 2603.42 | H9: 2476.24 | I9: 2439.87 | J9: 8.33 | K9: 12.395882 | L9: 🟡 Deposits at 90.8% - Need push (₹239Cr gap) | ✅ Advances at 101.5% - Strong performance | 🔴 CRITICAL: NPA at 8.33% - Immediate action needed | M9: Intensify retail deposit campaigns | Focus on salary account acquisition | URGENT: Constitute daily recovery task force | Legal action on top 5 defaulters | Offer OTS schemes to stressed accounts | N9: 2
A10: B1009 | B10: Branch_9 | C10: East | D10: A | E10: 81.1 | F10: 2850.64 | G10: 2941.49 | H10: 1926.8 | I10: 1532.77 | J10: 4.34 | K10: 3.595 | L10: ✅ Deposits at 96.9% - On track | ✅ Advances at 125.7% - Strong performance | 🟡 NPA at 4.34% - High stress zone | M10: Maintain momentum through customer engagement | Aggressive recovery campaigns | Weekly recovery review meetings | N10: 1
A11: B1010 | B11: Branch_10 | C11: North | D11: C | E11: 64.3 | F11: 360.92 | G11: 369.29 | H11: 636.93 | I11: 533.63 | J11: 10.87 | K11: 1.8083784 | L11: ✅ Deposits at 97.7% - On track | ✅ Advances at 119.4% - Strong performance | 🔴 CRITICAL: NPA at 10.87% - Immediate action needed | M11: Maintain momentum through customer engagement | URGENT: Constitute daily recovery task force | Legal action on top 5 defaulters | Offer OTS schemes to stressed accounts | CRITICAL: Review cost structure | N11: 1
A12: B1011 | B12: Branch_11 | C12: West | D12: C | E12: 64.4 | F12: 1374.32 | G12: 1844.02 | H12: 1490.92 | I12: 1304.22 | J12: 12.43 | K12: 4.8747368 | L12: 🔴 CRITICAL: Deposits at 74.5% of target (Need ₹470Cr more) | ✅ Advances at 114.3% - Strong performance | 🔴 CRITICAL: NPA at 12.43% - Immediate action needed | M12: URGENT: Launch deposit mobilization drive within 7 days | Target 5 new CASA accounts daily | Conduct customer meets in catchment area | URGENT: Constitute daily recovery task force | Legal action on top 5 defaulters | N12: 2
A13: B1012 | B13: Branch_12 | C13: South | D13: B | E13: 77.7 | F13: 1051.74 | G13: 1041.97 | H13: 1132.81 | I13: 1600.82 | J13: 1.62 | K13: 0.85077778 | L13: ✅ Deposits at 100.9% - On track | 🔴 CRITICAL: Advances at 70.8% (Need ₹468Cr) | 🟢 NPA at 1.62% - Manageable | M13: Maintain momentum through customer engagement | URGENT: Accelerate loan disbursement | Focus on MSME and Agriculture loans | Organize loan camps (2 per month) | Continue monitoring stress accounts | N13: 1
... A71: B1070 | B71: Branch_70 | C71: North | D71: A | E71: 86.5 | F71: 1517.32 | G71: 1861.55 | H71: 1875.68 | I71: 1809.39 | J71: 2.81 | K71: 4.5842857 | L71: 🔴 CRITICAL: Deposits at 81.5% of target (Need ₹344Cr more) | ✅ Advances at 103.7% - Strong performance | 🟢 NPA at 2.81% - Manageable | M71: URGENT: Launch deposit mobilization drive within 7 days | Target 5 new CASA accounts daily | Conduct customer meets in catchment area | Continue monitoring stress accounts | N71: 1

Sheet AI INSIGHTS & RECOMMENDATIONS
B2: 🤖 AI-POWERED BRANCH PERFORMANCE ANALYSIS
B4: Selected Branch: | C4: ='BRANCH PROFILE FULL FORMAT'!E9
B5: Overall Grade: | C5: =INDEX(DATA!D:D,MATCH('BRANCH PROFILE FULL FORMAT'!E9,DATA!B:B,0))
B6: Performance Score: | C6: =INDEX(DATA!E:E,MATCH('BRANCH PROFILE FULL FORMAT'!E9,DATA!B:B,0))
B9: 🎯 KEY INSIGHTS
B10: =INDEX(DATA!L:L,MATCH('BRANCH PROFILE FULL FORMAT'!E9,DATA!B:B,0))
B12: 💡 RECOMMENDED ACTIONS
B13: =INDEX(DATA!M:M,MATCH('BRANCH PROFILE FULL FORMAT'!E9,DATA!B:B,0))
B15: ⚡ PRIORITY ACTION ITEMS
B16: Priority actions are generated based on your performance gaps. Focus on P1-CRITICAL items first.

Sheet DAILY BUSINESS POSITION (DBP)
B2: 📊 DAILY BUSINESS POSITION (DBP)
B4: Branch: | C4: ='BRANCH PROFILE FULL FORMAT'!E9
B5: As on: 16-Jan-2026 vs 15-Jan-2026
B8: Parameter | C8: Previous Day | D8: Current Day | E8: Change | F8: % Change
B9: Total Deposits | C9: 0 | D9: 0 | E9: =D9-C9 | F9: =IF(C9<>0,(D9-C9)/C9*100,0)
B10: Total Advances | C10: 0 | D10: 0 | E10: =D10-C10 | F10: =IF(C10<>0,(D10-C10)/C10*100,0)
B11: CASA | C11: 0 | D11: 0 | E11: =D11-C11 | F11: =IF(C11<>0,(D11-C11)/C11*100,0)
B12: Gold Loan | C12: 0 | D12: 0 | E12: =D12-C12 | F12: =IF(C12<>0,(D12-C12)/C12*100,0)
B13: NPA % | C13: 0 | D13: 0 | E13: =D13-C13 | F13: =IF(C13<>0,(D13-C13)/C13*100,0)
B14: Advances/Deposits Ratio | C14: 0 | D14: 0 | E14: =D14-C14 | F14: =IF(C14<>0,(D14-C14)/C14*100,0)
B17: 📈 DAILY HIGHLIGHTS
B18: ✅ Positive movements are highlighted in green ⚠️ Negative movements are highlighted in red 📊 Daily tracking helps identify immediate trends 🎯 Focus on parameters showing negative change
