Workbook

Sheet BRANCH DASHBOARD
A1: BANK OF INDIA
A2: PLANNING DEPARTMENT - BRANCH PERFORMANCE DASHBOARD
B4: SELECT BRANCH: | E4: Branch_1 | F4: 👈 Select your branch from dropdown
B6: REPORT DATE: | E6: 13-Jan-2026
B8: शाखा विवरण / BRANCH DETAILS
B9: Branch ID: | E9: =INDEX(DATA!A:A,MATCH($E$5,DATA!B:B,0))
B10: Zone: | E10: =INDEX(DATA!C:C,MATCH($E$5,DATA!B:B,0))
B11: Grade: | E11: =INDEX(DATA!E:E,MATCH($E$5,DATA!B:B,0))
B12: Performance Score: | E12: =INDEX(DATA!D:D,MATCH($E$5,DATA!B:B,0))
B13: Risk Level: | E13: =INDEX(DATA!F:F,MATCH($E$5,DATA!B:B,0))
B15: जमा / DEPOSITS
B16: Category | C16: Mar-23 Actual | D16: Mar-24 Actual | E16: Mar-25 Actual | F16: Current Budget | G16: Current Actual | H16: GAP | I16: VAR Over Mar-25
B17: SAVINGS | C17: =INDEX(DATA!I:I,MATCH($E$5,DATA!B:B,0)) | D17: =INDEX(DATA!I:I,MATCH($E$5,DATA!B:B,0)) | E17: =INDEX(DATA!I:I,MATCH($E$5,DATA!B:B,0)) | F17: =INDEX(DATA!I:I,MATCH($E$5,DATA!B:B,0)) | G17: =INDEX(DATA!I:I,MATCH($E$5,DATA!B:B,0)) | H17: =F17-E17 | I17: =F17-D17
B18: CURRENT | C18: =INDEX(DATA!I:I,MATCH($E$5,DATA!B:B,0)) | D18: =INDEX(DATA!I:I,MATCH($E$5,DATA!B:B,0)) | E18: =INDEX(DATA!I:I,MATCH($E$5,DATA!B:B,0)) | F18: =INDEX(DATA!I:I,MATCH($E$5,DATA!B:B,0)) | G18: =INDEX(DATA!I:I,MATCH($E$5,DATA!B:B,0)) | H18: =F18-E18 | I18: =F18-D18
B19: CASA | C19: =INDEX(DATA!I:I,MATCH($E$5,DATA!B:B,0)) | D19: =INDEX(DATA!I:I,MATCH($E$5,DATA!B:B,0)) | E19: =INDEX(DATA!I:I,MATCH($E$5,DATA!B:B,0)) | F19: =INDEX(DATA!I:I,MATCH($E$5,DATA!B:B,0)) | G19: =INDEX(DATA!I:I,MATCH($E$5,DATA!B:B,0)) | H19: =F19-E19 | I19: =F19-D19
B20: RETAIL TD | C20: =INDEX(DATA!I:I,MATCH($E$5,DATA!B:B,0)) | D20: =INDEX(DATA!I:I,MATCH($E$5,DATA!B:B,0)) | E20: =INDEX(DATA!I:I,MATCH($E$5,DATA!B:B,0)) | F20: =INDEX(DATA!I:I,MATCH($E$5,DATA!B:B,0)) | G20: =INDEX(DATA!I:I,MATCH($E$5,DATA!B:B,0)) | H20: =F20-E20 | I20: =F20-D20
B21: TERM DEPOSITS | C21: =INDEX(DATA!I:I,MATCH($E$5,DATA!B:B,0)) | D21: =INDEX(DATA!I:I,MATCH($E$5,DATA!B:B,0)) | E21: =INDEX(DATA!I:I,MATCH($E$5,DATA!B:B,0)) | F21: =INDEX(DATA!I:I,MATCH($E$5,DATA!B:B,0)) | G21: =INDEX(DATA!I:I,MATCH($E$5,DATA!B:B,0)) | H21: =F21-E21 | I21: =F21-D21
B22: TOTAL DEPOSITS | C22: =INDEX(DATA!I:I,MATCH($E$5,DATA!B:B,0)) | D22: =INDEX(DATA!I:I,MATCH($E$5,DATA!B:B,0)) | E22: =INDEX(DATA!I:I,MATCH($E$5,DATA!B:B,0)) | F22: =INDEX(DATA!I:I,MATCH($E$5,DATA!B:B,0)) | G22: =INDEX(DATA!I:I,MATCH($E$5,DATA!B:B,0)) | H22: =F22-E22 | I22: =F22-D22
B24: अग्रिम / ADVANCES
B25: Category | C25: Mar-23 Actual | D25: Mar-24 Actual | E25: Mar-25 Actual | F25: Current Budget | G25: Current Actual | H25: GAP | I25: VAR Over Mar-25
B26: TOTAL ADVANCES | C26: =INDEX(DATA!K:K,MATCH($E$5,DATA!B:B,0)) | D26: =INDEX(DATA!K:K,MATCH($E$5,DATA!B:B,0)) | E26: =INDEX(DATA!K:K,MATCH($E$5,DATA!B:B,0)) | F26: =INDEX(DATA!K:K,MATCH($E$5,DATA!B:B,0)) | G26: =INDEX(DATA!K:K,MATCH($E$5,DATA!B:B,0)) | H26: =F26-E26 | I26: =F26-D26
B27: GOLD LOAN | C27: =INDEX(DATA!K:K,MATCH($E$5,DATA!B:B,0)) | D27: =INDEX(DATA!K:K,MATCH($E$5,DATA!B:B,0)) | E27: =INDEX(DATA!K:K,MATCH($E$5,DATA!B:B,0)) | F27: =INDEX(DATA!K:K,MATCH($E$5,DATA!B:B,0)) | G27: =INDEX(DATA!K:K,MATCH($E$5,DATA!B:B,0)) | H27: =F27-E27 | I27: =F27-D27
B28: AGRICULTURE | C28: =INDEX(DATA!K:K,MATCH($E$5,DATA!B:B,0)) | D28: =INDEX(DATA!K:K,MATCH($E$5,DATA!B:B,0)) | E28: =INDEX(DATA!K:K,MATCH($E$5,DATA!B:B,0)) | F28: =INDEX(DATA!K:K,MATCH($E$5,DATA!B:B,0)) | G28: =INDEX(DATA!K:K,MATCH($E$5,DATA!B:B,0)) | H28: =F28-E28 | I28: =F28-D28
B29: MSME | C29: =INDEX(DATA!K:K,MATCH($E$5,DATA!B:B,0)) | D29: =INDEX(DATA!K:K,MATCH($E$5,DATA!B:B,0)) | E29: =INDEX(DATA!K:K,MATCH($E$5,DATA!B:B,0)) | F29: =INDEX(DATA!K:K,MATCH($E$5,DATA!B:B,0)) | G29: =INDEX(DATA!K:K,MATCH($E$5,DATA!B:B,0)) | H29: =F29-E29 | I29: =F29-D29
B30: TOTAL RETAIL | C30: =INDEX(DATA!K:K,MATCH($E$5,DATA!B:B,0)) | D30: =INDEX(DATA!K:K,MATCH($E$5,DATA!B:B,0)) | E30: =INDEX(DATA!K:K,MATCH($E$5,DATA!B:B,0)) | F30: =INDEX(DATA!K:K,MATCH($E$5,DATA!B:B,0)) | G30: =INDEX(DATA!K:K,MATCH($E$5,DATA!B:B,0)) | H30: =F30-E30 | I30: =F30-D30
B31: CORPORATE & OTHERS | C31: =INDEX(DATA!K:K,MATCH($E$5,DATA!B:B,0)) | D31: =INDEX(DATA!K:K,MATCH($E$5,DATA!B:B,0)) | E31: =INDEX(DATA!K:K,MATCH($E$5,DATA!B:B,0)) | F31: =INDEX(DATA!K:K,MATCH($E$5,DATA!B:B,0)) | G31: =INDEX(DATA!K:K,MATCH($E$5,DATA!B:B,0)) | H31: =F31-E31 | I31: =F31-D31
B33: लाभप्रदता / PROFITABILITY
B34: PARAMETER | C34: Mar-23 Actual | D34: Mar-24 Actual | E34: Current Budget | F34: Current Actual | G34: GAP
B35: Interest Income | C35: =INDEX(DATA!N:N,MATCH($E$5,DATA!B:B,0)) | D35: =INDEX(DATA!N:N,MATCH($E$5,DATA!B:B,0)) | E35: =INDEX(DATA!N:N,MATCH($E$5,DATA!B:B,0)) | F35: =INDEX(DATA!N:N,MATCH($E$5,DATA!B:B,0)) | G35: =E35-D35
B36: Non-Interest Income | C36: =INDEX(DATA!N:N,MATCH($E$5,DATA!B:B,0)) | D36: =INDEX(DATA!N:N,MATCH($E$5,DATA!B:B,0)) | E36: =INDEX(DATA!N:N,MATCH($E$5,DATA!B:B,0)) | F36: =INDEX(DATA!N:N,MATCH($E$5,DATA!B:B,0)) | G36: =E36-D36
B37: Total Income | C37: =INDEX(DATA!N:N,MATCH($E$5,DATA!B:B,0)) | D37: =INDEX(DATA!N:N,MATCH($E$5,DATA!B:B,0)) | E37: =INDEX(DATA!N:N,MATCH($E$5,DATA!B:B,0)) | F37: =INDEX(DATA!N:N,MATCH($E$5,DATA!B:B,0)) | G37: =E37-D37
B38: Operating Expenses | C38: =INDEX(DATA!N:N,MATCH($E$5,DATA!B:B,0)) | D38: =INDEX(DATA!N:N,MATCH($E$5,DATA!B:B,0)) | E38: =INDEX(DATA!N:N,MATCH($E$5,DATA!B:B,0)) | F38: =INDEX(DATA!N:N,MATCH($E$5,DATA!B:B,0)) | G38: =E38-D38
B39: Net Profit | C39: =INDEX(DATA!N:N,MATCH($E$5,DATA!B:B,0)) | D39: =INDEX(DATA!N:N,MATCH($E$5,DATA!B:B,0)) | E39: =INDEX(DATA!N:N,MATCH($E$5,DATA!B:B,0)) | F39: =INDEX(DATA!N:N,MATCH($E$5,DATA!B:B,0)) | G39: =E39-D39
B42: KEY FOCUS AREAS
B43: Top Risk: | E43: =INDEX(DATA!G:G,MATCH($E$5,DATA!B:B,0))
B44: Priority Action: | E44: =INDEX(DATA!H:H,MATCH($E$5,DATA!B:B,0))

Sheet DATA
A1: Branch_ID | B1: Branch_Name | C1: Zone | D1: Score | E1: Grade | F1: Risk_Level | G1: Top_Risk | H1: Priority_Focus | I1: Total_Deposits | J1: Deposit_Target | K1: Advances | L1: Advance_Target | M1: NPA_Percent | N1: Profit_Per_Staff | O1: Savings_Mar23 | P1: Savings_Mar24 | Q1: Savings_Mar25 | R1: Current_Mar23 | S1: Current_Mar24 | T1: Current_Mar25
A2: B1002 | B2: Branch_2 | C2: Central | D2: 100 | E2: A | F2: Low | G2: No major risks identified | H2: Sustain performance | I2: 879.69 | J2: 668.71 | K2: 1287.25 | L2: 1197.78 | M2: 1.3 | N2: 7.6117647 | O2: 0 | P2: 0 | Q2: 0 | R2: 0 | S2: 0 | T2: 0
A3: B1003 | B3: Branch_3 | C3: North | D3: 93.1 | E3: A | F3: Low | G3: Advances below target | H3: Push quality credit growth | I3: 2002.69 | J3: 2219.18 | K3: 360.84 | L3: 429.1 | M3: 1.13 | N3: 9.0169767 | O3: 0 | P3: 0 | Q3: 0 | R3: 0 | S3: 0 | T3: 0
A4: B1004 | B4: Branch_4 | C4: South | D4: 74.2 | E4: B | F4: Medium | G4: High NPA levels | H4: Aggressive recovery & monitoring | I4: 1431.68 | J4: 1544.04 | K4: 1684.38 | L4: 1971.05 | M4: 8.35 | N4: 5.4928302 | O4: 0 | P4: 0 | Q4: 0 | R4: 0 | S4: 0 | T4: 0
A5: B1005 | B5: Branch_5 | C5: West | D5: 62.6 | E5: C | F5: High | G5: High NPA levels | H5: Aggressive recovery & monitoring | I5: 563.06 | J5: 674.81 | K5: 1667.36 | L5: 2024.6 | M5: 10.99 | N5: 3.3571875 | O5: 0 | P5: 0 | Q5: 0 | R5: 0 | S5: 0 | T5: 0
A6: B1006 | B6: Branch_6 | C6: North | D6: 73.7 | E6: B | F6: Medium | G6: High NPA levels | H6: Aggressive recovery & monitoring | I6: 1276.27 | J6: 1115.33 | K6: 667.39 | L6: 890.88 | M6: 7.59 | N6: 6.2707937 | O6: 0 | P6: 0 | Q6: 0 | R6: 0 | S6: 0 | T6: 0
A7: B1007 | B7: Branch_7 | C7: East | D7: 70.1 | E7: B | F7: Medium | G7: High NPA levels | H7: Aggressive recovery & monitoring | I7: 1077.43 | J7: 1493.45 | K7: 506.97 | L7: 539.21 | M7: 13.1 | N7: 13.036667 | O7: 0 | P7: 0 | Q7: 0 | R7: 0 | S7: 0 | T7: 0
A8: B1008 | B8: Branch_8 | C8: East | D8: 77.2 | E8: B | F8: Medium | G8: High NPA levels | H8: Aggressive recovery & monitoring | I8: 2364.34 | J8: 2603.42 | K8: 2476.24 | L8: 2439.87 | M8: 8.33 | N8: 12.395882 | O8: 0 | P8: 0 | Q8: 0 | R8: 0 | S8: 0 | T8: 0
A9: B1009 | B9: Branch_9 | C9: East | D9: 81.1 | E9: A | F9: Low | G9: Moderate NPA stress | H9: Strengthen credit monitoring | I9: 2850.64 | J9: 2941.49 | K9: 1926.8 | L9: 1532.77 | M9: 4.34 | N9: 3.595 | O9: 0 | P9: 0 | Q9: 0 | R9: 0 | S9: 0 | T9: 0
A10: B1010 | B10: Branch_10 | C10: North | D10: 64.3 | E10: C | F10: High | G10: Low profit per staff | H10: Improve staff productivity | I10: 360.92 | J10: 369.29 | K10: 636.93 | L10: 533.63 | M10: 10.87 | N10: 1.8083784 | O10: 0 | P10: 0 | Q10: 0 | R10: 0 | S10: 0 | T10: 0
A11: B1011 | B11: Branch_11 | C11: West | D11: 64.4 | E11: C | F11: High | G11: High NPA levels | H11: Aggressive recovery & monitoring | I11: 1374.32 | J11: 1844.02 | K11: 1490.92 | L11: 1304.22 | M11: 12.43 | N11: 4.8747368 | O11: 0 | P11: 0 | Q11: 0 | R11: 0 | S11: 0 | T11: 0
A12: B1012 | B12: Branch_12 | C12: South | D12: 77.7 | E12: B | F12: Medium | G12: Low profit per staff | H12: Improve staff productivity | I12: 1051.74 | J12: 1041.97 | K12: 1132.81 | L12: 1600.82 | M12: 1.62 | N12: 0.85077778 | O12: 0 | P12: 0 | Q12: 0 | R12: 0 | S12: 0 | T12: 0
A13: B1013 | B13: Branch_13 | C13: North | D13: 63.9 | E13: C | F13: High | G13: Low profit per staff | H13: Improve staff productivity | I13: 930.01 | J13: 966.72 | K13: 1731.72 | L13: 1640.04 | M13: 6.16 | N13: 2.2111538 | O13: 0 | P13: 0 | Q13: 0 | R13: 0 | S13: 0 | T13: 0
... A70: B1070 | B70: Branch_70 | C70: North | D70: 86.5 | E70: A | F70: Low | G70: No major risks identified | H70: Sustain performance | I70: 1517.32 | J70: 1861.55 | K70: 1875.68 | L70: 1809.39 | M70: 2.81 | N70: 4.5842857 | O70: 0 | P70: 0 | Q70: 0 | R70: 0 | S70: 0 | T70: 0
